viral_verify/__init__.py
viral_verify/cli.py
viral_verify/contig.py
viral_verify/io.py
viral_verify/log.py
viral_verify/prodigal.py
viral_verify/data/classifier_table.txt
viral_verify/hmmsearch/__init__.py
viral_verify/hmmsearch/constants.py
viral_verify/hmmsearch/io.py
viral_verify/hmmsearch/process.py
viral_verify/hmmsearch/result.py
viral_verify/naive_bayes/__init__.py
viral_verify/naive_bayes/classification.py
viral_verify/naive_bayes/constants.py
viral_verify/naive_bayes/io.py
viral_verify-0.1.1.dist-info/AUTHORS.rst
viral_verify-0.1.1.dist-info/LICENSE
viral_verify-0.1.1.dist-info/METADATA
viral_verify-0.1.1.dist-info/WHEEL
viral_verify-0.1.1.dist-info/entry_points.txt
viral_verify-0.1.1.dist-info/top_level.txt
viral_verify-0.1.1.dist-info/RECORD
