Metadata-Version: 2.1
Name: viral-verify
Version: 0.1.1
Summary: viralVerify rewrite/refactor for PyPI packaging and distribution
Home-page: https://github.com/peterk87/viral_verify
Author: Peter Kruczkiewicz
Author-email: peter.kruczkiewicz@gmail.com
License: MIT license
Keywords: viral_verify
Platform: UNKNOWN
Classifier: Development Status :: 2 - Pre-Alpha
Classifier: Intended Audience :: Developers
Classifier: License :: OSI Approved :: MIT License
Classifier: Natural Language :: English
Classifier: Programming Language :: Python :: 3
Classifier: Programming Language :: Python :: 3.6
Classifier: Programming Language :: Python :: 3.7
Classifier: Programming Language :: Python :: 3.8
Requires-Python: >=3.6
Requires-Dist: Click (>=7.0)
Requires-Dist: biopython (>=1.76)
Requires-Dist: pandas
Requires-Dist: attrs
